LinearFold.cpython-39-darwin.so
LinearFold-1.1.dist-info/AUTHORS
LinearFold-1.1.dist-info/LICENSE
LinearFold-1.1.dist-info/METADATA
LinearFold-1.1.dist-info/WHEEL
LinearFold-1.1.dist-info/top_level.txt
LinearFold-1.1.dist-info/RECORD
