Metadata-Version: 2.1
Name: LinearFold
Version: 1.1
Summary: A a tool to predict RNA secondary structure and minimum free energy
Home-page: https://github.com/LinearFold/LinearFold
Author: Katelyn McNair, Liang Huang*, He Zhang**, Dezhong Deng**, Kai Zhao, Kaibo Liu, David Hendrix, David Mathews
Author-email: deprekate@gmail.com
Classifier: Programming Language :: Python :: 3
Classifier: License :: OSI Approved :: GNU General Public License v3 or later (GPLv3+)
Classifier: Operating System :: OS Independent
Requires-Python: >3.5.2
License-File: LICENSE
License-File: AUTHORS
